oimalib/.DS_Store
oimalib/__init__.py
oimalib/__main__.py
oimalib/_cli.py
oimalib/alex.py
oimalib/binary.py
oimalib/classPure.py
oimalib/complex_models.py
oimalib/data_processing.py
oimalib/fitting.py
oimalib/fourier.py
oimalib/modelling.py
oimalib/models.py
oimalib/oifits.py
oimalib/pcs.py
oimalib/plotting.py
oimalib/tools.py
oimalib/fit/.DS_Store
oimalib/fit/__init__.py
oimalib/fit/dpfit.py
oimalib/fit/dpfunc.py
oimalib/internal_data/.DS_Store
oimalib/internal_data/colors.py
oimalib/internal_data/gravity_example.fits
oimalib/internal_data/u-v_plan_CITau.fits
oimalib-0.3.dist-info/entry_points.txt
oimalib-0.3.dist-info/licenses/LICENSE
oimalib-0.3.dist-info/WHEEL
oimalib-0.3.dist-info/METADATA
oimalib-0.3.dist-info/RECORD
