Metadata-Version: 2.4
Name: oimalib
Version: 0.3
Summary: Optical Interferometry Modelling and Analysis Library
Author-email: Anthony Soulain <anthony.soulain@oca.eu>
Requires-Python: >=3.10
Classifier: Development Status :: 5 - Production/Stable
Classifier: Intended Audience :: Science/Research
Classifier: License :: OSI Approved :: MIT License
Classifier: Operating System :: MacOS :: MacOS X
Classifier: Operating System :: POSIX :: AIX
Classifier: Operating System :: POSIX :: Linux
Classifier: Programming Language :: Python :: 3
Classifier: Programming Language :: Python :: 3 :: Only
Classifier: Topic :: Scientific/Engineering :: Astronomy
Classifier: Typing :: Typed
License-File: LICENSE
Requires-Dist: astropy>=5.0.1
Requires-Dist: astroquery>=0.4.4
Requires-Dist: scipy>=1.7.2
Requires-Dist: rich>=13.5.2
Requires-Dist: corner>=2.2.1
Requires-Dist: emcee>3.1.2
Requires-Dist: matplotlib>=3.5.0
Requires-Dist: numpy>=1.21.2
Requires-Dist: pypdf>=3.2.0
Requires-Dist: uncertainties>=3.1.6
Requires-Dist: h5py>=3.14.0
Requires-Dist: tqdm>=4.67.1
Requires-Dist: termcolor>=3.1.0
Requires-Dist: pandas>=2.3.3
Requires-Dist: munch>=4.0.0
Requires-Dist: seaborn>=0.13.2
Requires-Dist: pytest>=8 ; extra == "dev"
Requires-Dist: coverage>=7 ; extra == "dev"
Requires-Dist: ruff>=0.6.0 ; extra == "dev"
Requires-Dist: basedpyright>=1.19.0 ; extra == "dev"
Requires-Dist: ipykernel ; extra == "dev"
Requires-Dist: pre-commit ; extra == "dev"
Project-URL: Homepage, https://github.com/DrSoulain/oimalib
Project-URL: Issues, https://github.com/DrSoulain/oimalib/issues
Provides-Extra: dev
